inotify_lite/__init__.py
inotify_lite/inotify.py
inotify_lite/inotify_lite.py
tests/__init__.py
tests/test_inotify.py
inotify_lite-0.0.6.dist-info/LICENSE
inotify_lite-0.0.6.dist-info/METADATA
inotify_lite-0.0.6.dist-info/WHEEL
inotify_lite-0.0.6.dist-info/top_level.txt
inotify_lite-0.0.6.dist-info/RECORD
