Metadata-Version: 2.1
Name: inotify-lite
Version: 0.0.6
Summary: Linux inotify wrapper
Home-page: https://github.com/jams2/inotify_lite
Author: Joshua Munn
Author-email: public@elysee-munn.family
License: UNKNOWN
Platform: UNKNOWN
Classifier: Development Status :: 3 - Alpha
Classifier: Programming Language :: Python :: 3
Classifier: License :: OSI Approved :: GNU General Public License v3 or later (GPLv3+)
Classifier: Operating System :: POSIX :: Linux
Requires-Python: >=3.6
Provides-Extra: dev
Requires-Dist: pytest ; extra == 'dev'
Requires-Dist: pytest-mypy ; extra == 'dev'
Requires-Dist: pytest-flake8 ; extra == 'dev'
Provides-Extra: dist
Requires-Dist: setuptools ; extra == 'dist'
Requires-Dist: wheel ; extra == 'dist'
Requires-Dist: twine ; extra == 'dist'
Provides-Extra: docs
Requires-Dist: sphinx ; extra == 'docs'
